{
    "current_level": [
        {
            "value": 7.0,
            "churned": 500.0,
            "retained": 725.0
        },
        {
            "value": 1.0,
            "churned": 620.0,
            "retained": 1025.0
        },
        {
            "value": 4.0,
            "churned": 2150.0,
            "retained": 2505.0
        },
        {
            "value": 3.0,
            "churned": 492.0,
            "retained": 801.0
        },
        {
            "value": 2.0,
            "churned": 747.0,
            "retained": 804.0
        },
        {
            "value": 6.0,
            "churned": 557.0,
            "retained": 700.0
        },
        {
            "value": 5.0,
            "churned": 462.0,
            "retained": 740.0
        }
    ]
}